topsis.py
Topsis_Mohit_102197021-0.0.1.dist-info/LICENSE
Topsis_Mohit_102197021-0.0.1.dist-info/METADATA
Topsis_Mohit_102197021-0.0.1.dist-info/WHEEL
Topsis_Mohit_102197021-0.0.1.dist-info/top_level.txt
Topsis_Mohit_102197021-0.0.1.dist-info/RECORD
