Metadata-Version: 2.1
Name: Topsis-Mohit-102197021
Version: 0.0.1
Summary: multiple criteria decision making using topsis
Author: Mohit
Author-email: singlamohit444@gmail.com
Classifier: Programming Language :: Python :: 3
Classifier: Programming Language :: Python :: 3.6
Classifier: Programming Language :: Python :: 3.7
Classifier: License :: OSI Approved :: GNU General Public License v2 or later (GPLv2+)
Classifier: Operating System :: OS Independent
License-File: LICENSE
Requires-Dist: pandas (~=1.5.2)
Provides-Extra: dev
Requires-Dist: pytest (>=3.7) ; extra == 'dev'
